scripts/test/testsplinepdf.py
scripts/test/testsplinepdf2d.py
wums/__init__.py
wums/boostHistHelpers.py
wums/fitutils.py
wums/fitutilsjax.py
wums/ioutils.py
wums/logging.py
wums/output_tools.py
wums/plot_tools.py
wums/tfutils.py
wums/Templates/index.php
wums-0.1.8.dist-info/METADATA
wums-0.1.8.dist-info/WHEEL
wums-0.1.8.dist-info/top_level.txt
wums-0.1.8.dist-info/RECORD
